pytrex/__init__.py
pytrex/common.py
pytrex/text_opts.py
pytrex/trex_app.py
pytrex/trex_capture.py
pytrex/trex_object.py
pytrex/trex_port.py
pytrex/trex_statistics_view.py
pytrex/trex_stl_packet_builder_scapy.py
pytrex/trex_stream.py
pytrex/zipmsg.py
pytrex/api/__init__.py
pytrex/api/trex_event.py
pytrex/api/trex_stl_async_client.py
pytrex/api/trex_stl_conn.py
pytrex/api/trex_stl_jsonrpc_client.py
pytrex/api/trex_stl_types.py
pytrex-0.9.3.dist-info/METADATA
pytrex-0.9.3.dist-info/WHEEL
pytrex-0.9.3.dist-info/top_level.txt
pytrex-0.9.3.dist-info/RECORD
